binance2delta/__init__.py
binance2delta/converter.py
binance2delta/crawler.py
binance2delta/transaction.py
binance2delta/parser/__init__.py
binance2delta/parser/binance.py
binance2delta/parser/delta.py
binance2delta/parser/parser.py
binance2delta/parser (Kopie)/__init__.py
binance2delta/parser (Kopie)/binance.py
binance2delta/parser (Kopie)/delta.py
binance2delta/parser (Kopie)/parser.py
deltaconv/__init__.py
deltaconv/converter.py
deltaconv/crawler.py
deltaconv/transaction.py
deltaconv/parser/__init__.py
deltaconv/parser/binance.py
deltaconv/parser/bitpanda.py
deltaconv/parser/delta.py
deltaconv/parser/parser.py
tradingconv-1.3.0.dist-info/METADATA
tradingconv-1.3.0.dist-info/RECORD
tradingconv-1.3.0.dist-info/WHEEL
tradingconv-1.3.0.dist-info/entry_points.txt
tradingconv-1.3.0.dist-info/top_level.txt
