Metadata-Version: 2.1
Name: tradingconv
Version: 1.3.0
Summary: Package with tools to generate/convert csv|xlsx files for importing transactions into Delta or tax return software.
Home-page: UNKNOWN
Author: Lars Klitzke
Author-email: Lars.Klitzke@gmail.com
License: UNKNOWN
Platform: UNKNOWN
Classifier: Operating System :: OS Independent
Classifier: Programming Language :: Python :: 3.5
Classifier: Programming Language :: Python :: 3.6
Classifier: Programming Language :: Python :: 3.7
Classifier: License :: OSI Approved :: GNU Lesser General Public License v3 or later (LGPLv3+)
Classifier: Natural Language :: English
Requires-Dist: requests
Requires-Dist: xlrd
Requires-Dist: xlwt
